CONTRIBUTING.md
LICENSE
MANIFEST.in
README.rst
RELEASE_NOTES
eb
eb_bash_completion.bash
eb_bash_completion_local.bash
minimal_bash_completion.bash
optcomplete.bash
setup.cfg
setup.py
contrib/hooks/README.rst
contrib/hooks/add_delete_configopt.py
contrib/hooks/hpc2n_hooks.py
easybuild/__init__.py
easybuild/_deprecated.py
easybuild/main.py
easybuild/base/__init__.py
easybuild/base/exceptions.py
easybuild/base/fancylogger.py
easybuild/base/frozendict.py
easybuild/base/generaloption.py
easybuild/base/optcomplete.py
easybuild/base/rest.py
easybuild/base/testing.py
easybuild/base/wrapper.py
easybuild/framework/__init__.py
easybuild/framework/easyblock.py
easybuild/framework/easystack.py
easybuild/framework/extension.py
easybuild/framework/extensioneasyblock.py
easybuild/framework/easyconfig/__init__.py
easybuild/framework/easyconfig/constants.py
easybuild/framework/easyconfig/default.py
easybuild/framework/easyconfig/easyconfig.py
easybuild/framework/easyconfig/licenses.py
easybuild/framework/easyconfig/parser.py
easybuild/framework/easyconfig/style.py
easybuild/framework/easyconfig/templates.py
easybuild/framework/easyconfig/tools.py
easybuild/framework/easyconfig/tweak.py
easybuild/framework/easyconfig/types.py
easybuild/framework/easyconfig/format/__init__.py
easybuild/framework/easyconfig/format/convert.py
easybuild/framework/easyconfig/format/format.py
easybuild/framework/easyconfig/format/one.py
easybuild/framework/easyconfig/format/pyheaderconfigobj.py
easybuild/framework/easyconfig/format/two.py
easybuild/framework/easyconfig/format/version.py
easybuild/scripts/EasyBuild-reinstall-dev.sh
easybuild/scripts/clean_gists.py
easybuild/scripts/createSubmoduleDeps.sh
easybuild/scripts/findPythonDeps.py
easybuild/scripts/findUpdatedEcs.sh
easybuild/scripts/fix_docs.py
easybuild/scripts/install-EasyBuild-develop.sh
easybuild/scripts/install-EasyBuild-sprint.sh
easybuild/scripts/install_eb_dep.sh
easybuild/scripts/mk_tmpl_easyblock_for.py
easybuild/scripts/rpath_args.py
easybuild_framework.egg-info/PKG-INFO
easybuild_framework.egg-info/SOURCES.txt
easybuild_framework.egg-info/dependency_links.txt
easybuild_framework.egg-info/top_level.txt
